{
    "sourceFile": "src/app/components/crear-foro/crear-foro.component.html",
    "activeCommit": 0,
    "commits": [
        {
            "activePatchIndex": 25,
            "patches": [
                {
                    "date": 1719979732707,
                    "content": "Index: \n===================================================================\n--- \n+++ \n"
                },
                {
                    "date": 1719980203585,
                    "content": "Index: \n===================================================================\n--- \n+++ \n@@ -1,6 +1,8 @@\n+<app-header></app-header>\r\n+<div class=\"division\">\r\n+  <app-aside></app-aside>\r\n \r\n-\r\n <div class=\"container mt-5 d-flex justify-content-center\">\r\n     <div class=\"card bg-dark text-white\" style=\"width: 500px;\">\r\n       <div class=\"card-header text-center\">\r\n         <h2>CREAR FORO</h2>\r\n"
                },
                {
                    "date": 1719980210558,
                    "content": "Index: \n===================================================================\n--- \n+++ \n@@ -1,9 +1,8 @@\n <app-header></app-header>\r\n <div class=\"division\">\r\n   <app-aside></app-aside>\r\n-\r\n-<div class=\"container mt-5 d-flex justify-content-center\">\r\n+  <div class=\"container mt-5 d-flex justify-content-center\">\r\n     <div class=\"card bg-dark text-white\" style=\"width: 500px;\">\r\n       <div class=\"card-header text-center\">\r\n         <h2>CREAR FORO</h2>\r\n       </div>\r\n@@ -39,5 +38,6 @@\n         </form>\r\n       </div>\r\n     </div>\r\n   </div>\r\n-  \r\n+\r\n+</div>\n\\ No newline at end of file\n"
                },
                {
                    "date": 1719980416405,
                    "content": "Index: \n===================================================================\n--- \n+++ \n@@ -1,8 +1,8 @@\n <app-header></app-header>\r\n <div class=\"division\">\r\n   <app-aside></app-aside>\r\n-  <div class=\"container mt-5 d-flex justify-content-center\">\r\n+  <div class=\"container d-flex justify-content-center\">\r\n     <div class=\"card bg-dark text-white\" style=\"width: 500px;\">\r\n       <div class=\"card-header text-center\">\r\n         <h2>CREAR FORO</h2>\r\n       </div>\r\n"
                },
                {
                    "date": 1719981992316,
                    "content": "Index: \n===================================================================\n--- \n+++ \n@@ -6,9 +6,9 @@\n       <div class=\"card-header text-center\">\r\n         <h2>CREAR FORO</h2>\r\n       </div>\r\n       <div class=\"card-body\">\r\n-        <form>\r\n+        <form >\r\n           <div class=\"form-group mb-3\">\r\n             <label for=\"codigo\">Código:</label>\r\n             <input type=\"text\" class=\"form-control\" id=\"codigo\" placeholder=\"Código\">\r\n           </div>\r\n"
                },
                {
                    "date": 1719982010430,
                    "content": "Index: \n===================================================================\n--- \n+++ \n@@ -6,9 +6,9 @@\n       <div class=\"card-header text-center\">\r\n         <h2>CREAR FORO</h2>\r\n       </div>\r\n       <div class=\"card-body\">\r\n-        <form >\r\n+        <form (ngSubmit)=\"login(credentialsForm.value)\" #credentialsForm=\"ngForm\" >\r\n           <div class=\"form-group mb-3\">\r\n             <label for=\"codigo\">Código:</label>\r\n             <input type=\"text\" class=\"form-control\" id=\"codigo\" placeholder=\"Código\">\r\n           </div>\r\n"
                },
                {
                    "date": 1719982020784,
                    "content": "Index: \n===================================================================\n--- \n+++ \n@@ -6,9 +6,9 @@\n       <div class=\"card-header text-center\">\r\n         <h2>CREAR FORO</h2>\r\n       </div>\r\n       <div class=\"card-body\">\r\n-        <form (ngSubmit)=\"login(credentialsForm.value)\" #credentialsForm=\"ngForm\" >\r\n+        <form (ngSubmit)=\"login(credentialsForm.value)\" #form=\"ngForm\" >\r\n           <div class=\"form-group mb-3\">\r\n             <label for=\"codigo\">Código:</label>\r\n             <input type=\"text\" class=\"form-control\" id=\"codigo\" placeholder=\"Código\">\r\n           </div>\r\n"
                },
                {
                    "date": 1719982029645,
                    "content": "Index: \n===================================================================\n--- \n+++ \n@@ -6,9 +6,9 @@\n       <div class=\"card-header text-center\">\r\n         <h2>CREAR FORO</h2>\r\n       </div>\r\n       <div class=\"card-body\">\r\n-        <form (ngSubmit)=\"login(credentialsForm.value)\" #form=\"ngForm\" >\r\n+        <form (ngSubmit)=\"nuevoForo(formObject.value)\" #formObject=\"ngForm\" >\r\n           <div class=\"form-group mb-3\">\r\n             <label for=\"codigo\">Código:</label>\r\n             <input type=\"text\" class=\"form-control\" id=\"codigo\" placeholder=\"Código\">\r\n           </div>\r\n"
                },
                {
                    "date": 1719982511958,
                    "content": "Index: \n===================================================================\n--- \n+++ \n@@ -7,13 +7,10 @@\n         <h2>CREAR FORO</h2>\r\n       </div>\r\n       <div class=\"card-body\">\r\n         <form (ngSubmit)=\"nuevoForo(formObject.value)\" #formObject=\"ngForm\" >\r\n+\r\n           <div class=\"form-group mb-3\">\r\n-            <label for=\"codigo\">Código:</label>\r\n-            <input type=\"text\" class=\"form-control\" id=\"codigo\" placeholder=\"Código\">\r\n-          </div>\r\n-          <div class=\"form-group mb-3\">\r\n             <label for=\"titulo\">Título:</label>\r\n             <input type=\"text\" class=\"form-control\" id=\"titulo\" placeholder=\"Título\">\r\n           </div>\r\n           <div class=\"form-group mb-3\">\r\n"
                },
                {
                    "date": 1719982519833,
                    "content": "Index: \n===================================================================\n--- \n+++ \n@@ -7,9 +7,8 @@\n         <h2>CREAR FORO</h2>\r\n       </div>\r\n       <div class=\"card-body\">\r\n         <form (ngSubmit)=\"nuevoForo(formObject.value)\" #formObject=\"ngForm\" >\r\n-\r\n           <div class=\"form-group mb-3\">\r\n             <label for=\"titulo\">Título:</label>\r\n             <input type=\"text\" class=\"form-control\" id=\"titulo\" placeholder=\"Título\">\r\n           </div>\r\n@@ -29,9 +28,9 @@\n             </select>\r\n           </div>\r\n           <div class=\"d-flex justify-content-between\">\r\n             <button type=\"submit\" class=\"btn btn-primary\">Guardar</button>\r\n-            <button type=\"button\" class=\"btn btn-danger\">Cancelar</button>\r\n+            <button type=\"button\"  class=\"btn btn-danger\">Cancelar</button>\r\n           </div>\r\n         </form>\r\n       </div>\r\n     </div>\r\n"
                },
                {
                    "date": 1719982528255,
                    "content": "Index: \n===================================================================\n--- \n+++ \n@@ -28,9 +28,9 @@\n             </select>\r\n           </div>\r\n           <div class=\"d-flex justify-content-between\">\r\n             <button type=\"submit\" class=\"btn btn-primary\">Guardar</button>\r\n-            <button type=\"button\"  class=\"btn btn-danger\">Cancelar</button>\r\n+            <button type=\"button\" (click)=\"retornar()\" class=\"btn btn-danger\">Cancelar</button>\r\n           </div>\r\n         </form>\r\n       </div>\r\n     </div>\r\n"
                },
                {
                    "date": 1719982628837,
                    "content": "Index: \n===================================================================\n--- \n+++ \n@@ -24,8 +24,10 @@\n             <label for=\"categoria\">Categoría:</label>\r\n             <select class=\"form-control\" id=\"categoria\">\r\n               <option>Seleccionar</option>\r\n               <!-- Agregar opciones aquí -->\r\n+              <option *ngFor=\"let item of categoria\" [value]=\"item.categoriaHabilidadId\">{{item.nombre}}</option>\r\n+\r\n             </select>\r\n           </div>\r\n           <div class=\"d-flex justify-content-between\">\r\n             <button type=\"submit\" class=\"btn btn-primary\">Guardar</button>\r\n"
                },
                {
                    "date": 1719982635899,
                    "content": "Index: \n===================================================================\n--- \n+++ \n@@ -24,9 +24,9 @@\n             <label for=\"categoria\">Categoría:</label>\r\n             <select class=\"form-control\" id=\"categoria\">\r\n               <option>Seleccionar</option>\r\n               <!-- Agregar opciones aquí -->\r\n-              <option *ngFor=\"let item of categoria\" [value]=\"item.categoriaHabilidadId\">{{item.nombre}}</option>\r\n+              <option *ngFor=\"let item of categoriaForos\" [value]=\"item.categoriaId\">{{item.nombre}}</option>\r\n \r\n             </select>\r\n           </div>\r\n           <div class=\"d-flex justify-content-between\">\r\n"
                },
                {
                    "date": 1719982643049,
                    "content": "Index: \n===================================================================\n--- \n+++ \n@@ -24,9 +24,9 @@\n             <label for=\"categoria\">Categoría:</label>\r\n             <select class=\"form-control\" id=\"categoria\">\r\n               <option>Seleccionar</option>\r\n               <!-- Agregar opciones aquí -->\r\n-              <option *ngFor=\"let item of categoriaForos\" [value]=\"item.categoriaId\">{{item.nombre}}</option>\r\n+              <option *ngFor=\"let item of categoriaForos\" [value]=\"item.categoriaId\">{{item.}}</option>\r\n \r\n             </select>\r\n           </div>\r\n           <div class=\"d-flex justify-content-between\">\r\n"
                },
                {
                    "date": 1719982735107,
                    "content": "Index: \n===================================================================\n--- \n+++ \n@@ -24,9 +24,9 @@\n             <label for=\"categoria\">Categoría:</label>\r\n             <select class=\"form-control\" id=\"categoria\">\r\n               <option>Seleccionar</option>\r\n               <!-- Agregar opciones aquí -->\r\n-              <option *ngFor=\"let item of categoriaForos\" [value]=\"item.categoriaId\">{{item.}}</option>\r\n+              <option *ngFor=\"let item of categoriaForos\" [value]=\"item.categoriaId\">{{item.nombre}}</option>\r\n \r\n             </select>\r\n           </div>\r\n           <div class=\"d-flex justify-content-between\">\r\n"
                },
                {
                    "date": 1719982748747,
                    "content": "Index: \n===================================================================\n--- \n+++ \n@@ -9,9 +9,9 @@\n       <div class=\"card-body\">\r\n         <form (ngSubmit)=\"nuevoForo(formObject.value)\" #formObject=\"ngForm\" >\r\n           <div class=\"form-group mb-3\">\r\n             <label for=\"titulo\">Título:</label>\r\n-            <input type=\"text\" class=\"form-control\" id=\"titulo\" placeholder=\"Título\">\r\n+            <input type=\"text\" class=\"form-control\" id=\"titulo\" name=\"\" placeholder=\"Título\">\r\n           </div>\r\n           <div class=\"form-group mb-3\">\r\n             <label for=\"descripcion\">Descripción:</label>\r\n             <textarea class=\"form-control\" id=\"descripcion\" rows=\"3\" placeholder=\"Descripción\"></textarea>\r\n"
                },
                {
                    "date": 1719982760869,
                    "content": "Index: \n===================================================================\n--- \n+++ \n@@ -9,13 +9,13 @@\n       <div class=\"card-body\">\r\n         <form (ngSubmit)=\"nuevoForo(formObject.value)\" #formObject=\"ngForm\" >\r\n           <div class=\"form-group mb-3\">\r\n             <label for=\"titulo\">Título:</label>\r\n-            <input type=\"text\" class=\"form-control\" id=\"titulo\" name=\"\" placeholder=\"Título\">\r\n+            <input type=\"text\" class=\"form-control\" id=\"titulo\" name=\"titulo\" placeholder=\"Título\">\r\n           </div>\r\n           <div class=\"form-group mb-3\">\r\n             <label for=\"descripcion\">Descripción:</label>\r\n-            <textarea class=\"form-control\" id=\"descripcion\" rows=\"3\" placeholder=\"Descripción\"></textarea>\r\n+            <textarea class=\"form-control\" id=\"descripcion\" rows=\"3\" name=\"titulo\" placeholder=\"Descripción\"></textarea>\r\n           </div>\r\n           <div class=\"form-group mb-3\">\r\n             <label for=\"fechaCreacion\">Fecha Creación:</label>\r\n             <input type=\"date\" class=\"form-control\" id=\"fechaCreacion\" placeholder=\"Fecha Creación\">\r\n"
                },
                {
                    "date": 1719982800415,
                    "content": "Index: \n===================================================================\n--- \n+++ \n@@ -13,12 +13,12 @@\n             <input type=\"text\" class=\"form-control\" id=\"titulo\" name=\"titulo\" placeholder=\"Título\">\r\n           </div>\r\n           <div class=\"form-group mb-3\">\r\n             <label for=\"descripcion\">Descripción:</label>\r\n-            <textarea class=\"form-control\" id=\"descripcion\" rows=\"3\" name=\"titulo\" placeholder=\"Descripción\"></textarea>\r\n+            <textarea class=\"form-control\" id=\"descripcion\" rows=\"3\" name=\"descripcion\" placeholder=\"Descripción\"></textarea>\r\n           </div>\r\n           <div class=\"form-group mb-3\">\r\n-            <label for=\"fechaCreacion\">Fecha Creación:</label>\r\n+            <label for=\"fechaCreacion\">Fecha Creación:</label> \r\n             <input type=\"date\" class=\"form-control\" id=\"fechaCreacion\" placeholder=\"Fecha Creación\">\r\n           </div>\r\n           <div class=\"form-group mb-4\">\r\n             <label for=\"categoria\">Categoría:</label>\r\n"
                },
                {
                    "date": 1719982806198,
                    "content": "Index: \n===================================================================\n--- \n+++ \n@@ -17,9 +17,9 @@\n             <textarea class=\"form-control\" id=\"descripcion\" rows=\"3\" name=\"descripcion\" placeholder=\"Descripción\"></textarea>\r\n           </div>\r\n           <div class=\"form-group mb-3\">\r\n             <label for=\"fechaCreacion\">Fecha Creación:</label> \r\n-            <input type=\"date\" class=\"form-control\" id=\"fechaCreacion\" placeholder=\"Fecha Creación\">\r\n+            <input type=\"date\" class=\"form-control\" id=\"fechaCreacion\" name=\"fechaCreacion\" placeholder=\"Fecha Creación\">\r\n           </div>\r\n           <div class=\"form-group mb-4\">\r\n             <label for=\"categoria\">Categoría:</label>\r\n             <select class=\"form-control\" id=\"categoria\">\r\n"
                },
                {
                    "date": 1719982812567,
                    "content": "Index: \n===================================================================\n--- \n+++ \n@@ -21,9 +21,9 @@\n             <input type=\"date\" class=\"form-control\" id=\"fechaCreacion\" name=\"fechaCreacion\" placeholder=\"Fecha Creación\">\r\n           </div>\r\n           <div class=\"form-group mb-4\">\r\n             <label for=\"categoria\">Categoría:</label>\r\n-            <select class=\"form-control\" id=\"categoria\">\r\n+            <select class=\"form-control\" id=\"categoria\"  name=\"fechaCreacion\" >\r\n               <option>Seleccionar</option>\r\n               <!-- Agregar opciones aquí -->\r\n               <option *ngFor=\"let item of categoriaForos\" [value]=\"item.categoriaId\">{{item.nombre}}</option>\r\n \r\n"
                },
                {
                    "date": 1719982819455,
                    "content": "Index: \n===================================================================\n--- \n+++ \n@@ -21,9 +21,9 @@\n             <input type=\"date\" class=\"form-control\" id=\"fechaCreacion\" name=\"fechaCreacion\" placeholder=\"Fecha Creación\">\r\n           </div>\r\n           <div class=\"form-group mb-4\">\r\n             <label for=\"categoria\">Categoría:</label>\r\n-            <select class=\"form-control\" id=\"categoria\"  name=\"fechaCreacion\" >\r\n+            <select class=\"form-control\" id=\"categoria\">\r\n               <option>Seleccionar</option>\r\n               <!-- Agregar opciones aquí -->\r\n               <option *ngFor=\"let item of categoriaForos\" [value]=\"item.categoriaId\">{{item.nombre}}</option>\r\n \r\n"
                },
                {
                    "date": 1719983076995,
                    "content": "Index: \n===================================================================\n--- \n+++ \n@@ -9,9 +9,9 @@\n       <div class=\"card-body\">\r\n         <form (ngSubmit)=\"nuevoForo(formObject.value)\" #formObject=\"ngForm\" >\r\n           <div class=\"form-group mb-3\">\r\n             <label for=\"titulo\">Título:</label>\r\n-            <input type=\"text\" class=\"form-control\" id=\"titulo\" name=\"titulo\" placeholder=\"Título\">\r\n+            <input type=\"text\" class=\"form-control\" id=\"titulo\" name=\"titulo\" placeholder=\"Título\" ngModel>\r\n           </div>\r\n           <div class=\"form-group mb-3\">\r\n             <label for=\"descripcion\">Descripción:</label>\r\n             <textarea class=\"form-control\" id=\"descripcion\" rows=\"3\" name=\"descripcion\" placeholder=\"Descripción\"></textarea>\r\n"
                },
                {
                    "date": 1719983084483,
                    "content": "Index: \n===================================================================\n--- \n+++ \n@@ -13,13 +13,13 @@\n             <input type=\"text\" class=\"form-control\" id=\"titulo\" name=\"titulo\" placeholder=\"Título\" ngModel>\r\n           </div>\r\n           <div class=\"form-group mb-3\">\r\n             <label for=\"descripcion\">Descripción:</label>\r\n-            <textarea class=\"form-control\" id=\"descripcion\" rows=\"3\" name=\"descripcion\" placeholder=\"Descripción\"></textarea>\r\n+            <textarea class=\"form-control\" id=\"descripcion\" rows=\"3\" name=\"descripcion\" placeholder=\"Descripción\" ngModel></textarea>\r\n           </div>\r\n           <div class=\"form-group mb-3\">\r\n             <label for=\"fechaCreacion\">Fecha Creación:</label> \r\n-            <input type=\"date\" class=\"form-control\" id=\"fechaCreacion\" name=\"fechaCreacion\" placeholder=\"Fecha Creación\">\r\n+            <input type=\"date\" class=\"form-control\" id=\"fechaCreacion\" name=\"fechaCreacion\" placeholder=\"Fecha Creación\" ngModel>\r\n           </div>\r\n           <div class=\"form-group mb-4\">\r\n             <label for=\"categoria\">Categoría:</label>\r\n             <select class=\"form-control\" id=\"categoria\">\r\n"
                },
                {
                    "date": 1719983293060,
                    "content": "Index: \n===================================================================\n--- \n+++ \n@@ -6,9 +6,9 @@\n       <div class=\"card-header text-center\">\r\n         <h2>CREAR FORO</h2>\r\n       </div>\r\n       <div class=\"card-body\">\r\n-        <form (ngSubmit)=\"nuevoForo(formObject.value)\" #formObject=\"ngForm\" >\r\n+        <form (ngSubmit)=\"nuevoForo(formObject.value)\" #formObject=\"ngForm\">\r\n           <div class=\"form-group mb-3\">\r\n             <label for=\"titulo\">Título:</label>\r\n             <input type=\"text\" class=\"form-control\" id=\"titulo\" name=\"titulo\" placeholder=\"Título\" ngModel>\r\n           </div>\r\n@@ -16,18 +16,16 @@\n             <label for=\"descripcion\">Descripción:</label>\r\n             <textarea class=\"form-control\" id=\"descripcion\" rows=\"3\" name=\"descripcion\" placeholder=\"Descripción\" ngModel></textarea>\r\n           </div>\r\n           <div class=\"form-group mb-3\">\r\n-            <label for=\"fechaCreacion\">Fecha Creación:</label> \r\n+            <label for=\"fechaCreacion\">Fecha Creación:</label>\r\n             <input type=\"date\" class=\"form-control\" id=\"fechaCreacion\" name=\"fechaCreacion\" placeholder=\"Fecha Creación\" ngModel>\r\n           </div>\r\n           <div class=\"form-group mb-4\">\r\n             <label for=\"categoria\">Categoría:</label>\r\n-            <select class=\"form-control\" id=\"categoria\">\r\n-              <option>Seleccionar</option>\r\n-              <!-- Agregar opciones aquí -->\r\n-              <option *ngFor=\"let item of categoriaForos\" [value]=\"item.categoriaId\">{{item.nombre}}</option>\r\n-\r\n+            <select class=\"form-control\" id=\"categoria\" name=\"obj_CategoriaForo\" ngModel>\r\n+              <option value=\"\" disabled selected>Seleccionar</option>\r\n+              <option *ngFor=\"let item of categoriaForos\" [value]=\"item\">{{item.nombre}}</option>\r\n             </select>\r\n           </div>\r\n           <div class=\"d-flex justify-content-between\">\r\n             <button type=\"submit\" class=\"btn btn-primary\">Guardar</button>\r\n@@ -36,6 +34,5 @@\n         </form>\r\n       </div>\r\n     </div>\r\n   </div>\r\n-\r\n-</div>\n\\ No newline at end of file\n+</div>\r\n"
                },
                {
                    "date": 1719983506849,
                    "content": "Index: \n===================================================================\n--- \n+++ \n@@ -23,9 +23,9 @@\n           <div class=\"form-group mb-4\">\r\n             <label for=\"categoria\">Categoría:</label>\r\n             <select class=\"form-control\" id=\"categoria\" name=\"obj_CategoriaForo\" ngModel>\r\n               <option value=\"\" disabled selected>Seleccionar</option>\r\n-              <option *ngFor=\"let item of categoriaForos\" [value]=\"item\">{{item.nombre}}</option>\r\n+              <option *ngFor=\"let item of categoriaForos\" [value]=\"item.categoriaId\">{{item.nombre}}</option>\r\n             </select>\r\n           </div>\r\n           <div class=\"d-flex justify-content-between\">\r\n             <button type=\"submit\" class=\"btn btn-primary\">Guardar</button>\r\n"
                },
                {
                    "date": 1719984224085,
                    "content": "Index: \n===================================================================\n--- \n+++ \n@@ -21,9 +21,9 @@\n             <input type=\"date\" class=\"form-control\" id=\"fechaCreacion\" name=\"fechaCreacion\" placeholder=\"Fecha Creación\" ngModel>\r\n           </div>\r\n           <div class=\"form-group mb-4\">\r\n             <label for=\"categoria\">Categoría:</label>\r\n-            <select class=\"form-control\" id=\"categoria\" name=\"obj_CategoriaForo\" ngModel>\r\n+            <select class=\"form-control\" id=\"categoria\" name=\"categoriaId\" ngModel>\r\n               <option value=\"\" disabled selected>Seleccionar</option>\r\n               <option *ngFor=\"let item of categoriaForos\" [value]=\"item.categoriaId\">{{item.nombre}}</option>\r\n             </select>\r\n           </div>\r\n"
                }
            ],
            "date": 1719979732707,
            "name": "Commit-0",
            "content": "\r\n\r\n<div class=\"container mt-5 d-flex justify-content-center\">\r\n    <div class=\"card bg-dark text-white\" style=\"width: 500px;\">\r\n      <div class=\"card-header text-center\">\r\n        <h2>CREAR FORO</h2>\r\n      </div>\r\n      <div class=\"card-body\">\r\n        <form>\r\n          <div class=\"form-group mb-3\">\r\n            <label for=\"codigo\">Código:</label>\r\n            <input type=\"text\" class=\"form-control\" id=\"codigo\" placeholder=\"Código\">\r\n          </div>\r\n          <div class=\"form-group mb-3\">\r\n            <label for=\"titulo\">Título:</label>\r\n            <input type=\"text\" class=\"form-control\" id=\"titulo\" placeholder=\"Título\">\r\n          </div>\r\n          <div class=\"form-group mb-3\">\r\n            <label for=\"descripcion\">Descripción:</label>\r\n            <textarea class=\"form-control\" id=\"descripcion\" rows=\"3\" placeholder=\"Descripción\"></textarea>\r\n          </div>\r\n          <div class=\"form-group mb-3\">\r\n            <label for=\"fechaCreacion\">Fecha Creación:</label>\r\n            <input type=\"date\" class=\"form-control\" id=\"fechaCreacion\" placeholder=\"Fecha Creación\">\r\n          </div>\r\n          <div class=\"form-group mb-4\">\r\n            <label for=\"categoria\">Categoría:</label>\r\n            <select class=\"form-control\" id=\"categoria\">\r\n              <option>Seleccionar</option>\r\n              <!-- Agregar opciones aquí -->\r\n            </select>\r\n          </div>\r\n          <div class=\"d-flex justify-content-between\">\r\n            <button type=\"submit\" class=\"btn btn-primary\">Guardar</button>\r\n            <button type=\"button\" class=\"btn btn-danger\">Cancelar</button>\r\n          </div>\r\n        </form>\r\n      </div>\r\n    </div>\r\n  </div>\r\n  \r\n"
        }
    ]
}